Workbook

Sheet Leads
A1: Lead ID | B1: Date Created | C1: Name | D1: Email | E1: Phone | F1: Property Type | G1: Budget | H1: Timeline | I1: Message | J1: Lead Score | K1: Temperature | L1: Priority | M1: Qualification Reason | N1: Recommended Action | O1: Suggested Agent Type | P1: Assigned Agent | Q1: Agent Email | R1: Agent Phone | S1: Agent Specialty | T1: Lead Status | U1: Follow-Up Status | V1: Appointment Status | W1: Outcome | X1: Assigned Date | Y1: Last Contact Date | Z1: Next Follow-Up Date | AA1: Escalation Status
A2: LEAD-20260609-171329 | B2: 46182.718 | C2: Maria Lopez | D2: maria@example.com | E2: 9171234567 | F2: Residential | G2: 8000000 | H2: Within 30 days | I2: I am looking for a 3-bedroom house in Cavite and I want to schedule a viewing soon. | J2: 90 | K2: Hot | L2: High | M2: Urgent timeline of 30 days, clear intent to buy a 3-bedroom house, and strong budget of 8,000,000. | N2: Schedule a property viewing with Maria Lopez as soon as possible. | O2: Residential | P2: Anna Santos | Q2: anna@premierrealty.com | R2: 639171111111 | S2: Residential | T2: Assigned | U2: Not Started | V2: Not Booked | W2: Pending | X2: 46182.835 | AA2: Not Escalated
A3: LEAD-20260611-173738 | B3: 46184.734 | C3: Sofia Reyes | D3: sofia.reyes@example.com | E3: 9181234567 | F3: Condo | G3: 6500000 | H3: Within 30 days | I3: I am interested in a condo near BGC and would like to schedule a viewing soon. I already have financing ready. | J3: 90 | K3: Hot | L3: High | M3: Lead has a clear property type preference, strong budget, urgent timeline, and readiness for financing. | N3: Schedule a viewing appointment as soon as possible. | O3: Residential | P3: Anna Santos | Q3: anna@premierrealty.com | R3: 639171111111 | S3: Residential | T3: Assigned | U3: Not Started | V3: Not Booked | W3: Pending | X3: 46184.735 | AA3: Not Escalated
A4: LEAD-20260611-174231 | B4: 46184.738 | C4: Marco Tan | D4: marco.tan@example.com | E4: 9221234567 | F4: Commercial | G4: 15000000 | H4: ASAP | I4: I am looking for a commercial space for my business and need to schedule a call this week. Budget is ready and I want to move quickly. | J4: 90 | K4: Hot | L4: High | M4: Urgent timeline for a commercial property, clear buying intent, and strong budget of 15,000,000. | N4: Schedule a call with Marco this week to discuss commercial space options. | O4: Commercial | P4: Bob Reyes | Q4: inquiry.asdautomations@gmail.com | R4: 639171111111 | S4: Residential/Commercial | T4: Assigned | U4: Not Started | V4: Not Booked | W4: Pending | X4: 46184.738 | AA4: Not Escalated
A5: LEAD-20260611-174403 | B5: 46184.739 | C5: Lara Mendoza | D5: lara.mendoza@example.com | E5: 9331234567 | F5: Residential | G5: 4000000 | H5: In 3 to 6 months | I5: I am comparing houses in Cavite and Laguna. I am not in a rush yet but I would like to know available options. | J5: 60 | K5: Warm | L5: Medium | M5: Lara is interested in comparing options but has a non-urgent timeline of 3 to 6 months and hasn't requested a viewing. | N5: Follow up in a month to discuss available properties and options. | O5: Residential | P5: Bob Reyes | Q5: inquiry.asdautomations@gmail.com | R5: 639171111111 | S5: Residential / Commercial | T5: Assigned | U5: Not Started | V5: Not Booked | W5: Pending | X5: 46184.739 | AA5: Not Escalated
A6: LEAD-20260611-174439 | B6: 46184.739 | C6: Nico Ramos | D6: nico.ramos@example.com | E6: 9441234567 | F6: Residential | G6: 1000000 | H6: Not sure yet | I6: Just browsing for now. I am not sure what I want yet and I am only checking prices. | J6: 25 | K6: Cold | L6: Low | M6: Lead is just browsing with no urgency and unclear intent. | N6: Follow up in a few months to reassess interest. | O6: Residential | P6: Carl Cruz | Q6: inquiry.asdautomations@gmail.com | R6: 639171111111 | S6: Nuture / Cold Leads | T6: Assigned | U6: Not Started | V6: Not Booked | W6: Pending | X6: 46184.739 | AA6: Not Escalated

Sheet Activity Log
A1: Timestamp | B1: Lead ID | C1: Activity Type | D1: Description | E1: Agent | F1: Status | G1: Notes
A2: 2026-06-09 20:02:06 | B2: LEAD-20260609-171329 | C2: Lead Assigned | D2: Hot residential lead assigned to Anna Santos. | E2: Anna Santos | F2: Completed
A3: 46183.602 | B3: LEAD-20260610-125812 | C3: Agent Notified | D3: Telegram notification sent to Anna Santos | E3: Anna Santos | F3: Completed | G3: Assigned agent received lead details, AI score, priority, and recommended action.
A4: 46183.603 | B4: LEAD-20260610-125812 | C4: Acknowledgement Email Sent | D4: Acknowledgement email sent to maria@example.com | E4: Anna Santos | F4: Completed | G4: Automated confirmation email sent after lead was created in CRM.
A5: 46183.613 | B5: LEAD-20260610-125812 | C5: Follow-Up Scheduled | D5: First follow-up task scheduled for 2026-06-11 14:42:40 | E5: Anna Santos | F5: Completed | G5: Follow-up task automatically created in the Follow-Ups sheet.
A6: 46183.731 | B6: LEAD-20260610-125812 | C6: Follow-Up Sent | D6: Follow-up email sent to maria@example.com | E6: Anna Santos | F6: Completed | G6: Follow-up status updated to Sent in the Follow-Ups sheet.
A7: 46183.738 | B7: LEAD-20260610-125812 | C7: Follow-Up Sent | D7: Follow-up email sent to maria@example.com | E7: Anna Santos | F7: Completed | G7: Follow-up status updated to Sent in the Follow-Ups sheet.
A8: 46184.618 | B8: LEAD-20260610-125812 | C8: Escalation Sent | D8: Escalation alert sent for overdue follow-up assigned to Anna Santos | E8: Anna Santos | F8: Completed | G8: Manager or agent was notified through Telegram and follow-up row was marked as escalated.
A9: 46184.735 | B9: LEAD-20260611-173738 | C9: Agent Notified | D9: Telegram notification sent to Anna Santos | E9: Anna Santos | F9: Completed | G9: Assigned agent received lead details, AI score, priority, and recommended action.
A10: 46184.735 | B10: LEAD-20260611-173738 | C10: Acknowledgement Email Sent | D10: Acknowledgement email sent to sofia.reyes@example.com | E10: Anna Santos | F10: Completed | G10: Automated confirmation email sent after lead was created in CRM.
A11: 46184.735 | B11: LEAD-20260611-173738 | C11: Follow-Up Scheduled | D11: First follow-up task scheduled for 2026-06-12 17:37:55 | E11: Anna Santos | F11: Completed | G11: Follow-up task automatically created in the Follow-Ups sheet.
A12: 46184.738 | B12: LEAD-20260611-174231 | C12: Agent Notified | D12: Telegram notification sent to Bob Reyes | E12: Bob Reyes | F12: Completed | G12: Assigned agent received lead details, AI score, priority, and recommended action.
A13: 46184.738 | B13: LEAD-20260611-174231 | C13: Acknowledgement Email Sent | D13: Acknowledgement email sent to marco.tan@example.com | E13: Bob Reyes | F13: Completed | G13: Automated confirmation email sent after lead was created in CRM.
A14: 46184.738 | B14: LEAD-20260611-174231 | C14: Follow-Up Scheduled | D14: First follow-up task scheduled for 2026-06-12 17:42:45 | E14: Bob Reyes | F14: Completed | G14: Follow-up task automatically created in the Follow-Ups sheet.
... A25: 46184.742 | B25: LEAD-20260611-174439 | C25: Follow-Up Sent | D25: Follow-up email sent to nico.ramos@example.com | E25: Carl Cruz | F25: Completed | G25: Follow-up status updated to Sent in the Follow-Ups sheet.

Sheet Follow-Ups
A1: Lead ID | B1: Lead Name | C1: Lead Email | D1: Follow-Up Number | E1: Scheduled Date | F1: Status | G1: Sent Date | H1: Assigned Agent | I1: Email Type | J1: Priority | K1: Notes | L1: Escalation Status | M1: Escalated Date
A2: LEAD-20260610-125812 | B2: Maria Lopez | C2: maria@example.com | D2: 1 | E2: 46184.609 | F2: Sent | G2: 46184.742 | H2: Anna Santos | I2: Follow-Up 1 | J2: High | K2: Auto-scheduled after lead assignment | L2: Escalated | M2: 46184.616
A3: LEAD-20260611-173738 | B3: Sofia Reyes | C3: sofia.reyes@example.com | D3: 1 | E3: 46185.735 | F3: Sent | G3: 46184.742 | H3: Anna Santos | I3: Follow-Up 1 | J3: High | K3: Auto-scheduled after lead assignment
A4: LEAD-20260611-174231 | B4: Marco Tan | C4: marco.tan@example.com | D4: 1 | E4: 46185.738 | F4: Sent | G4: 46184.742 | H4: Bob Reyes | I4: Follow-Up 1 | J4: High | K4: Auto-scheduled after lead assignment
A5: LEAD-20260611-174403 | B5: Lara Mendoza | C5: lara.mendoza@example.com | D5: 1 | E5: 46185.739 | F5: Sent | G5: 46184.742 | H5: Bob Reyes | I5: Follow-Up 1 | J5: Medium | K5: Auto-scheduled after lead assignment
A6: LEAD-20260611-174439 | B6: Nico Ramos | C6: nico.ramos@example.com | D6: 1 | E6: 46185.739 | F6: Sent | G6: 46184.742 | H6: Carl Cruz | I6: Follow-Up 1 | J6: Low | K6: Auto-scheduled after lead assignment

Sheet Dashboard
A1: AI Sales Coordinator System Dashboard
A2: Metric | B2: Value
A3: Total Leads | B3: =COUNTA(Leads!A2:A1000) -> 5
A4: Hot Leads | B4: =COUNTIF(Leads!K2:K1000,"Hot") -> 3
A5: Warm Leads | B5: =COUNTIF(Leads!K2:K1000,"Warm") -> 1
A6: Cold Leads | B6: =COUNTIF(Leads!K2:K1000,"Cold") -> 1
A7: High Priority | B7: =COUNTIF(Leads!L2:L1000,"High") -> 3
A8: Assigned Leads | B8: =COUNTIF(Leads!T2:T1000,"Assigned") -> 5
A9: Appointments Booked | B9: =COUNTIF(Leads!V2:V1000,"Booked") -> 0
A10: Escalated Leads | B10: =COUNTIF(Leads!AA2:AA1000,"Escalated") -> 0
A11: Pending Follow-Ups | B11: =COUNTIF('Follow-Ups'!F:F,"Pending") -> 0
A12: Sent Follow-Ups | B12: =COUNTIF('Follow-Ups'!F:F,"Sent") -> 5
A13: Escalated Follow-Ups | B13: =COUNTIF('Follow-Ups'!L:L,"Escalated") -> 1
A14: Total Activities Logged | B14: =COUNTA('Activity Log'!C:C)-1 -> 24
A17: Leads Per Agent
A18: Anna Santos | B18: =COUNTIF(Leads!P2:P1000,"Anna Santos") -> 2
A19: Bob Reyes | B19: =COUNTIF(Leads!P2:P1000,"Bob Reyes") -> 2
A20: Carl Cruz | B20: =COUNTIF(Leads!P2:P1000,"Carl Cruz") -> 1
A22: Pipeline Status
A23: New | B23: =COUNTIF(Leads!T2:T1000,"New") -> 0
A24: Assigned | B24: =COUNTIF(Leads!T2:T1000,"Assigned") -> 5
A25: Contacted | B25: =COUNTIF(Leads!T2:T1000,"Contacted") -> 0
A26: Closed Won | B26: =COUNTIF(Leads!W2:W1000,"Closed Won") -> 0
A27: Closed Lost | B27: =COUNTIF(Leads!W2:W1000,"Closed Lost") -> 0
A30: Follow-Up Status
A31: Pending | B31: =COUNTIF('Follow-Ups'!F:F,"Pending") -> 0
A32: Sent | B32: =COUNTIF('Follow-Ups'!F:F,"Sent") -> 5
A33: Escalated | B33: =COUNTIF('Follow-Ups'!F:F,"Sent") -> 5
A35: Activity Log Summary
A36: Agent Notified | B36: =COUNTIF('Activity Log'!C:C,"Agent Notified") -> 5
A37: Acknowledgement Email Sent | B37: =COUNTIF('Activity Log'!C:C,"Acknowledgement Email Sent") -> 5
A38: Follow-Up Scheduled | B38: =COUNTIF('Activity Log'!C:C,"Follow-Up Scheduled") -> 5
A39: Follow-Up Sent | B39: =COUNTIF('Activity Log'!C:C,"Follow-Up Sent") -> 7
A40: Escalation Sent | B40: =COUNTIF('Activity Log'!C:C,"Escalation Sent") -> 1

Sheet Lists
A1: Property Type | B1: Temperature | C1: Priority | D1: Lead Status | E1: Follow-Up Status | F1: Appointment Status | G1: Outcome | H1: Escalation Status | I1: Assigned Agent
A2: Residential | B2: Hot | C2: High | D2: New | E2: Not Started | F2: Not Booked | G2: Pending | H2: Not Escalated | I2: Anna Santos
A3: Condo | B3: Warm | C3: Medium | D3: Assigned | E3: Follow-Up 1 Sent | F3: Booked | G3: Closed Won | H3: Escalated | I3: Bob Reyes
A4: Commercial | B4: Cold | C4: Low | D4: Contacted | E4: Follow-Up 2 Sent | F4: Cancelled | G4: Closed Lost | I4: Carl Cruz
A5: Other | D5: Qualified | E5: Completed | F5: Rescheduled | G5: Unresponsive
D6: Closed | E6: Paused
